perceptron_py_pi/__init__.py
perceptron_py_pi/perceptron.py
preceptron_pi_pi_atulb123-0.0.4.dist-info/LICENSE
preceptron_pi_pi_atulb123-0.0.4.dist-info/METADATA
preceptron_pi_pi_atulb123-0.0.4.dist-info/WHEEL
preceptron_pi_pi_atulb123-0.0.4.dist-info/top_level.txt
preceptron_pi_pi_atulb123-0.0.4.dist-info/RECORD
