Metadata-Version: 2.1
Name: preceptron-pi-pi-atulb123
Version: 0.0.4
Summary: implementation of perceptron
Home-page: https://github.com/atulb123/preceptron_pi_pi
Author: atulb123
Author-email: atulmysuru@example.com
License: UNKNOWN
Project-URL: Bug Tracker, https://github.com/atulb123/preceptron_pi_pi/issues
Platform: UNKNOWN
Classifier: Programming Language :: Python :: 3
Classifier: License :: OSI Approved :: MIT License
Classifier: Operating System :: OS Independent
Requires-Python: >=3.6
License-File: LICENSE
Requires-Dist: numpy
Requires-Dist: matplotlib
Requires-Dist: pandas
Requires-Dist: joblib
